llm_error_handler/__init__.py
llm_error_handler/error_handling.py
llm_error_handler/test.py
llm_error_handler/llms/__init__.py
llm_error_handler/llms/all_llms/__init__.py
llm_error_handler/llms/all_llms/chat_llm.py
llm_error_handler/llms/configs/__init__.py
llm_error_handler/llms/configs/llm_configs/__init__.py
llm_error_handler/llms/configs/llm_configs/llm_models.json
llm_error_handler/llms/gemini/__init__.py
llm_error_handler/llms/gemini/change_utils.py
llm_error_handler/llms/gemini/gemini_chat_history.py
llm_error_handler/llms/gemini/gemini_chat_llm.py
llm_error_handler/llms/llm_utils/__init__.py
llm_error_handler/llms/llm_utils/adjust_llm_json.py
llm_error_handler/llms/llm_utils/get_embedding.py
llm_error_handler/llms/llm_utils/mix_in.py
llm_error_handler/llms/llm_utils/stream_json.py
llm_error_handler/llms/llm_utils/word_similarity.py
llm_error_handler/llms/openai/__init__.py
llm_error_handler/llms/openai/openai_assistant_chat.py
llm_error_handler/llms/openai/openai_chat_history.py
llm_error_handler/llms/openai/openai_chat_llm.py
llm_error_handler/prompt/__init__.py
llm_error_handler/prompt/error_handling_prompt.txt
llm_error_handler/venv/__init__.py
llm_error_handler-0.2.15.dist-info/METADATA
llm_error_handler-0.2.15.dist-info/WHEEL
llm_error_handler-0.2.15.dist-info/top_level.txt
llm_error_handler-0.2.15.dist-info/RECORD
